ws_ui/__init__.py
ws_ui/__main__.py
ws_ui-1.0.0.data/scripts/ws-ui
ws_ui-1.0.0.dist-info/METADATA
ws_ui-1.0.0.dist-info/WHEEL
ws_ui-1.0.0.dist-info/top_level.txt
ws_ui-1.0.0.dist-info/RECORD
