Metadata-Version: 2.1
Name: ws-ui
Version: 1.0.0
Summary: shell shortcut
Home-page: UNKNOWN
Author: Abraham
Author-email: abraham.liu@hotmail.com
License: UNKNOWN
Platform: UNKNOWN
Classifier: Programming Language :: Python :: 3
Classifier: Operating System :: OS Independent
Requires-Dist: tornado
Requires-Dist: prompt-toolkit
